CHANGES.rst
CONTRIBUTORS.rst
LICENSE.txt
MANIFEST.in
README.rst
setup.py
bin/edeposit_harvester_test.py
docs/Makefile
docs/__init__.py
docs/conf.py
docs/index.rst
docs/uzivatelska_prirucka.rst
docs/api/harvester.autoparser.conf_reader.rst
docs/api/harvester.autoparser.generator.rst
docs/api/harvester.autoparser.path_patterns.rst
docs/api/harvester.autoparser.rst
docs/api/harvester.autoparser.utils.rst
docs/api/harvester.autoparser.vectors.rst
docs/api/harvester.edeposit_autoparser.rst
docs/api/harvester.filters.aleph_filter.rst
docs/api/harvester.filters.dup_filter.rst
docs/api/harvester.filters.rst
docs/api/harvester.rst
docs/api/harvester.scrappers.ben_cz.rst
docs/api/harvester.scrappers.cpress_cz.rst
docs/api/harvester.scrappers.grada_cz.rst
docs/api/harvester.scrappers.rst
docs/api/harvester.scrappers.utils.rst
docs/api/harvester.scrappers.zonerpress_cz.rst
docs/api/harvester.settings.rst
docs/api/harvester.structures.rst
docs/api/modules.rst
docs/scripts/edeposit_harvester_test.rst
src/edeposit/__init__.py
src/edeposit.amqp.harvester.egg-info/PKG-INFO
src/edeposit.amqp.harvester.egg-info/SOURCES.txt
src/edeposit.amqp.harvester.egg-info/dependency_links.txt
src/edeposit.amqp.harvester.egg-info/namespace_packages.txt
src/edeposit.amqp.harvester.egg-info/not-zip-safe
src/edeposit.amqp.harvester.egg-info/requires.txt
src/edeposit.amqp.harvester.egg-info/top_level.txt
src/edeposit/amqp/__init__.py
src/edeposit/amqp/harvester/__init__.py
src/edeposit/amqp/harvester/edeposit_autoparser.py
src/edeposit/amqp/harvester/settings.py
src/edeposit/amqp/harvester/structures.py
src/edeposit/amqp/harvester/autoparser/__init__.py
src/edeposit/amqp/harvester/autoparser/conf_reader.py
src/edeposit/amqp/harvester/autoparser/generator.py
src/edeposit/amqp/harvester/autoparser/path_patterns.py
src/edeposit/amqp/harvester/autoparser/utils.py
src/edeposit/amqp/harvester/autoparser/vectors.py
src/edeposit/amqp/harvester/filters/__init__.py
src/edeposit/amqp/harvester/filters/aleph_filter.py
src/edeposit/amqp/harvester/filters/dup_filter.py
src/edeposit/amqp/harvester/scrappers/__init__.py
src/edeposit/amqp/harvester/scrappers/ben_cz.py
src/edeposit/amqp/harvester/scrappers/cpress_cz.py
src/edeposit/amqp/harvester/scrappers/grada_cz.py
src/edeposit/amqp/harvester/scrappers/utils.py
