Metadata-Version: 1.1
Name: edeposit.amqp.harvester
Version: 1.0.1
Summary: Metadata harvester of the books printed by specific publishers.
Home-page: https://github.com/edeposit/edeposit.amqp.harvester/
Author: Edeposit team
Author-email: edeposit@email.cz
License: MIT
Platform: UNKNOWN
Classifier: Programming Language :: Python :: 2.7
Classifier: License :: OSI Approved :: MIT License
Classifier: Topic :: Software Development :: Libraries :: Python Modules
